{
  "BV1DEkEB3E99": {
    "startTime": 123.69,
    "endTime": 144.66,
    "duration": 20.97,
    "updatedAt": "2026-02-04T10:48:17.615Z"
  },
  "BV1DSzjBhEci": {
    "startTime": 95.65,
    "endTime": 116.02,
    "duration": 20.37,
    "updatedAt": "2026-02-04T10:54:11.537Z"
  },
  "BV13hrrBBERp": {
    "startTime": 67.31,
    "endTime": 87.31,
    "duration": 20,
    "updatedAt": "2026-02-04T10:55:20.966Z"
  },
  "BV1uDrSBoE3x": {
    "startTime": 34.1,
    "endTime": 54.1,
    "duration": 20,
    "updatedAt": "2026-02-04T10:56:38.299Z"
  },
  "BV1iMr5BBEDf": {
    "startTime": 64.59,
    "endTime": 84.59,
    "duration": 20,
    "updatedAt": "2026-02-05T03:16:27.867Z"
  },
  "BV1YckHBnEGx": {
    "startTime": 7.78,
    "endTime": 27.78,
    "duration": 20,
    "updatedAt": "2026-02-04T10:58:18.144Z"
  },
  "BV1hhzMBrEmL": {
    "startTime": 29.34,
    "endTime": 49.34,
    "duration": 20,
    "updatedAt": "2026-02-04T11:00:13.047Z"
  },
  "BV1UarDBZEw9": {
    "startTime": 66.17,
    "endTime": 90,
    "duration": 23.83,
    "updatedAt": "2026-02-04T11:05:35.451Z"
  },
  "BV1VJzLBAEyP": {
    "startTime": 53.99,
    "endTime": 74.5,
    "duration": 20.51,
    "updatedAt": "2026-02-04T11:07:13.502Z"
  },
  "BV1TrkPBFEzL": {
    "startTime": 33.67,
    "endTime": 56.21,
    "duration": 22.54,
    "updatedAt": "2026-02-04T11:07:49.628Z"
  },
  "BV15GmhBaEZF": {
    "startTime": 12.63,
    "endTime": 32.63,
    "duration": 20,
    "updatedAt": "2026-02-05T03:30:56.841Z"
  },
  "BV17NrWBaE87": {
    "startTime": 35.81,
    "endTime": 55.81,
    "duration": 20,
    "updatedAt": "2026-02-04T11:09:45.546Z"
  },
  "BV1SBk7BBESE": {
    "startTime": 81.66,
    "endTime": 101.66,
    "duration": 20,
    "updatedAt": "2026-02-04T11:12:27.591Z"
  },
  "BV1V6iDBREbc": {
    "startTime": 52.41,
    "endTime": 74.2,
    "duration": 21.79,
    "updatedAt": "2026-02-05T03:31:08.112Z"
  },
  "BV1JT69BUEvA": {
    "startTime": 26.83,
    "endTime": 46.5,
    "duration": 19.67,
    "updatedAt": "2026-02-05T03:39:14.705Z"
  },
  "BV132kGBZEMJ": {
    "startTime": 70.8,
    "endTime": 90.4,
    "duration": 19.6,
    "updatedAt": "2026-02-04T11:17:42.549Z"
  },
  "BV1cXrrBWEu9": {
    "startTime": 39.47,
    "endTime": 60.9,
    "duration": 21.43,
    "updatedAt": "2026-02-04T11:21:29.668Z"
  },
  "BV1dh6DBvEyf": {
    "startTime": 61.61,
    "endTime": 83.9,
    "duration": 22.29,
    "updatedAt": "2026-02-05T03:08:52.033Z"
  },
  "BV1xZqmBzECT": {
    "startTime": 44,
    "endTime": 68.75,
    "duration": 24.75,
    "updatedAt": "2026-02-04T11:26:37.433Z"
  },
  "BV1c4iEB5ECw": {
    "startTime": 66.1,
    "endTime": 87.3,
    "duration": 21.2,
    "updatedAt": "2026-02-05T03:39:55.137Z"
  },
  "BV1iZiMBGEd8": {
    "startTime": 37.3,
    "endTime": 57.3,
    "duration": 20,
    "updatedAt": "2026-02-05T03:40:39.385Z"
  },
  "BV1zBq6BuEyH": {
    "startTime": 37,
    "endTime": 56,
    "duration": 19,
    "updatedAt": "2026-02-05T05:11:26.500Z"
  },
  "BV1pnHWzkE4j": {
    "startTime": 43.9,
    "endTime": 63,
    "duration": 19.1,
    "updatedAt": "2026-02-05T05:05:15.173Z"
  },
  "BV1JThqzwEGq": {
    "startTime": 40.5,
    "endTime": 69.9,
    "duration": 29.4,
    "updatedAt": "2026-02-05T05:04:51.404Z"
  },
  "BV1YZzpBJELG": {
    "startTime": 37.18,
    "endTime": 57.18,
    "duration": 20,
    "updatedAt": "2026-02-04T11:39:04.780Z"
  },
  "BV1kti8BGEco": {
    "startTime": 26.1,
    "endTime": 49.12,
    "duration": 23.02,
    "updatedAt": "2026-02-05T03:41:55.545Z"
  },
  "BV1s7rBBSEK1": {
    "startTime": 31.8,
    "endTime": 56.8,
    "duration": 25,
    "updatedAt": "2026-02-05T03:46:31.800Z"
  },
  "BV148tzzVEoK": {
    "startTime": 92.79,
    "endTime": 112.79,
    "duration": 20,
    "updatedAt": "2026-02-05T05:04:00.018Z"
  },
  "BV1DFhmz2Ehn": {
    "startTime": 38.6,
    "endTime": 58.6,
    "duration": 20,
    "updatedAt": "2026-02-04T11:47:41.364Z"
  },
  "BV1qDUPYKEzf": {
    "startTime": 40.5,
    "endTime": 60.5,
    "duration": 20,
    "updatedAt": "2026-02-04T11:49:06.773Z"
  },
  "BV14VrKBAEnT": {
    "startTime": 45.4,
    "endTime": 63.61,
    "duration": 18.21,
    "updatedAt": "2026-02-05T03:03:17.924Z"
  },
  "BV17cieB7E1U": {
    "startTime": 56.31,
    "endTime": 75.93,
    "duration": 19.62,
    "updatedAt": "2026-02-05T03:11:27.731Z"
  },
  "BV1qirKB7Ehh": {
    "startTime": 41.1,
    "endTime": 59.53,
    "duration": 18.43,
    "updatedAt": "2026-02-05T03:16:09.976Z"
  },
  "BV1GE6QBYE1d": {
    "startTime": 39,
    "endTime": 58.95,
    "duration": 19.95,
    "updatedAt": "2026-02-05T03:18:33.057Z"
  },
  "BV1zmrABGENp": {
    "startTime": 45.29,
    "endTime": 65.29,
    "duration": 20,
    "updatedAt": "2026-02-05T03:20:07.033Z"
  },
  "BV1oqiXBeEV9": {
    "startTime": 46.66,
    "endTime": 67.6,
    "duration": 20.94,
    "updatedAt": "2026-02-05T03:24:48.785Z"
  },
  "BV14PivBPEGo": {
    "startTime": 55,
    "endTime": 76,
    "duration": 21,
    "updatedAt": "2026-02-05T03:28:54.457Z"
  },
  "BV1Lfi7BYE8y": {
    "startTime": 73.65,
    "endTime": 93.65,
    "duration": 20,
    "updatedAt": "2026-02-05T03:30:36.192Z"
  },
  "BV1KX25BTEUq": {
    "startTime": 166.7,
    "endTime": 191,
    "duration": 24.3,
    "updatedAt": "2026-02-05T03:47:58.417Z"
  },
  "BV1ucGzzuEhw": {
    "startTime": 56.5,
    "endTime": 76.9,
    "duration": 20.4,
    "updatedAt": "2026-02-05T03:49:33.840Z"
  },
  "BV12PrpBVE3S": {
    "startTime": 3.5,
    "endTime": 27,
    "duration": 23.5,
    "updatedAt": "2026-02-05T03:54:58.817Z"
  },
  "BV1H1vaB1E53": {
    "startTime": 74,
    "endTime": 94.5,
    "duration": 20.5,
    "updatedAt": "2026-02-05T05:13:13.229Z"
  },
  "BV1ZcKdzDE5Q": {
    "startTime": 54.5,
    "endTime": 74.1,
    "duration": 19.6,
    "updatedAt": "2026-02-05T05:23:32.372Z"
  },
  "BV1EY4y1V71F": {
    "startTime": 70,
    "endTime": 93,
    "duration": 23,
    "updatedAt": "2026-02-05T05:28:59.015Z"
  },
  "BV1wCkFBGEKm": {
    "startTime": 59,
    "endTime": 78.3,
    "duration": 19.3,
    "updatedAt": "2026-02-05T05:31:49.973Z"
  },
  "BV1GW6dB1Ewg": {
    "startTime": 48.5,
    "endTime": 71,
    "duration": 22.5,
    "updatedAt": "2026-02-05T05:34:47.837Z"
  },
  "BV1EYiTB6Eyv": {
    "startTime": 2.7,
    "endTime": 24.4,
    "duration": 21.7,
    "updatedAt": "2026-02-05T05:38:30.148Z"
  },
  "BV1PXfRBkE8Q": {
    "startTime": 44.5,
    "endTime": 66.5,
    "duration": 22,
    "updatedAt": "2026-02-07T05:27:20.384Z"
  },
  "BV1Xy61BnEUG": {
    "startTime": 81.18,
    "endTime": 101.18,
    "duration": 20,
    "updatedAt": "2026-02-07T05:29:05.224Z"
  },
  "BV19EFaz8E2F": {
    "startTime": 0.7,
    "endTime": 22.29,
    "duration": 21.59,
    "updatedAt": "2026-02-07T05:29:55.953Z"
  },
  "BV19U6VBtEx6": {
    "startTime": 37.69,
    "endTime": 57.69,
    "duration": 20,
    "updatedAt": "2026-02-07T05:30:39.040Z"
  },
  "BV1iv6nBnE8s": {
    "startTime": 72.5,
    "endTime": 91.88,
    "duration": 19.38,
    "updatedAt": "2026-02-07T05:33:00.680Z"
  },
  "BV1frFzzoEdu": {
    "startTime": 128.4,
    "endTime": 152.56,
    "duration": 24.16,
    "updatedAt": "2026-02-07T05:39:01.508Z"
  },
  "BV1go6PBwEMu": {
    "startTime": 56.85,
    "endTime": 81.85,
    "duration": 25,
    "updatedAt": "2026-02-07T05:41:00.981Z"
  },
  "BV1GSBZBUEoi": {
    "startTime": 99.6,
    "endTime": 123.49,
    "duration": 23.89,
    "updatedAt": "2026-02-07T05:43:41.912Z"
  },
  "BV1TL61B3EiF": {
    "startTime": 66.6,
    "endTime": 87.15,
    "duration": 20.55,
    "updatedAt": "2026-02-07T05:51:20.927Z"
  },
  "BV1hr6EBBEqV": {
    "startTime": 65.2,
    "endTime": 91.43,
    "duration": 26.23,
    "updatedAt": "2026-02-07T05:52:40.126Z"
  },
  "BV1dTzRBCEkg": {
    "startTime": 26.3,
    "endTime": 50.46,
    "duration": 24.16,
    "updatedAt": "2026-02-07T05:54:33.509Z"
  },
  "BV1RWzMBjEob": {
    "startTime": 36.78,
    "endTime": 56.78,
    "duration": 20,
    "updatedAt": "2026-02-07T05:55:01.853Z"
  },
  "BV15HFVz1EvM": {
    "startTime": 25.08,
    "endTime": 48.42,
    "duration": 23.34,
    "updatedAt": "2026-02-07T05:56:36.131Z"
  },
  "BV1nY6sBuEqn": {
    "startTime": 45.77,
    "endTime": 74.49,
    "duration": 28.72,
    "updatedAt": "2026-02-07T05:58:22.042Z"
  },
  "BV1ZrzuBXEhA": {
    "startTime": 48.92,
    "endTime": 67.09,
    "duration": 18.17,
    "updatedAt": "2026-02-07T06:01:19.091Z"
  },
  "BV1uDffB8ExP": {
    "startTime": 64.3,
    "endTime": 84.3,
    "duration": 20,
    "updatedAt": "2026-02-07T06:02:56.320Z"
  },
  "BV11SF6z3E9r": {
    "startTime": 151,
    "endTime": 176.1,
    "duration": 25.1,
    "updatedAt": "2026-02-07T06:04:44.782Z"
  },
  "BV1Ww6cBGEXq": {
    "startTime": 70.4,
    "endTime": 91.17,
    "duration": 20.77,
    "updatedAt": "2026-02-07T06:05:42.619Z"
  },
  "BV1ek61BDEd2": {
    "startTime": 49.22,
    "endTime": 70.03,
    "duration": 20.81,
    "updatedAt": "2026-02-07T06:06:52.204Z"
  },
  "BV1fkzaBHEh4": {
    "startTime": 44.4,
    "endTime": 73,
    "duration": 28.6,
    "updatedAt": "2026-02-07T06:09:06.436Z"
  },
  "BV1bNFhznEeS": {
    "startTime": 13.82,
    "endTime": 34.32,
    "duration": 20.5,
    "updatedAt": "2026-02-07T06:10:40.805Z"
  },
  "BV11pzEBoES9": {
    "startTime": 49.3,
    "endTime": 73.05,
    "duration": 23.75,
    "updatedAt": "2026-02-07T06:12:10.888Z"
  },
  "BV1ibzyBUEaS": {
    "startTime": 50.63,
    "endTime": 74.78,
    "duration": 24.15,
    "updatedAt": "2026-02-07T06:13:10.896Z"
  },
  "BV1bzvfBeEwR": {
    "startTime": 72.6,
    "endTime": 92.6,
    "duration": 20,
    "updatedAt": "2026-02-09T06:43:12.868Z"
  },
  "BV1amvZBuE7d": {
    "startTime": 73.2,
    "endTime": 92.96,
    "duration": 19.76,
    "updatedAt": "2026-02-09T06:44:55.907Z"
  },
  "BV1opiGBQEPh": {
    "startTime": 68.7,
    "endTime": 90.8,
    "duration": 22.1,
    "updatedAt": "2026-02-09T06:47:45.623Z"
  },
  "BV1NYvXB5E25": {
    "startTime": 155.2,
    "endTime": 177.7,
    "duration": 22.5,
    "updatedAt": "2026-02-09T06:55:54.156Z"
  },
  "BV1vBqwBREST": {
    "startTime": 60.7,
    "endTime": 83.2,
    "duration": 22.5,
    "updatedAt": "2026-02-09T06:56:34.435Z"
  },
  "BV1kJ6EBXEJ8": {
    "startTime": 55.5,
    "endTime": 76.33,
    "duration": 20.83,
    "updatedAt": "2026-02-09T06:57:10.603Z"
  },
  "BV1R1zTBGEFp": {
    "startTime": 0.4,
    "endTime": 26.8,
    "duration": 26.4,
    "updatedAt": "2026-02-09T06:57:31.977Z"
  },
  "BV1EqzTBUEtc": {
    "startTime": 41.7,
    "endTime": 61.6,
    "duration": 19.9,
    "updatedAt": "2026-02-09T06:58:01.689Z"
  },
  "BV17ozBBKEHP": {
    "startTime": 74.4,
    "endTime": 98.1,
    "duration": 23.7,
    "updatedAt": "2026-02-09T06:59:09.851Z"
  },
  "BV1qxzgBXETa": {
    "startTime": 25.3,
    "endTime": 44.1,
    "duration": 18.8,
    "updatedAt": "2026-02-09T06:59:47.208Z"
  },
  "BV19iFQzSEpQ": {
    "startTime": 34.3,
    "endTime": 55.7,
    "duration": 21.4,
    "updatedAt": "2026-02-14T03:36:22.663Z"
  },
  "BV1WSFSzAETQ": {
    "startTime": 53.58,
    "endTime": 73.58,
    "duration": 20,
    "updatedAt": "2026-02-14T03:37:34.507Z"
  },
  "BV1VvF7zpEpx": {
    "startTime": 54.5,
    "endTime": 74.07,
    "duration": 19.57,
    "updatedAt": "2026-02-14T03:38:33.191Z"
  },
  "BV1ypFWzREcy": {
    "startTime": 60.6,
    "endTime": 82.2,
    "duration": 21.6,
    "updatedAt": "2026-02-14T03:40:36.278Z"
  },
  "BV1ZhFkzwE65": {
    "startTime": 10.09,
    "endTime": 30.73,
    "duration": 20.64,
    "updatedAt": "2026-02-14T03:41:36.336Z"
  },
  "BV1WzFCz1Ej5": {
    "startTime": 61.02,
    "endTime": 83.13,
    "duration": 22.11,
    "updatedAt": "2026-02-14T05:06:37.114Z"
  },
  "BV1prcKzkExL": {
    "startTime": 78.62,
    "endTime": 98.62,
    "duration": 20,
    "updatedAt": "2026-02-14T05:08:53.975Z"
  },
  "BV1c9FmzQEkh": {
    "startTime": 48.26,
    "endTime": 71.13,
    "duration": 22.87,
    "updatedAt": "2026-02-14T05:10:04.475Z"
  },
  "BV1W8cwzeEr1": {
    "startTime": 90.12,
    "endTime": 111.42,
    "duration": 21.3,
    "updatedAt": "2026-02-14T05:12:42.403Z"
  },
  "BV1CyFpzDEub": {
    "startTime": 80.01,
    "endTime": 102.61,
    "duration": 22.6,
    "updatedAt": "2026-02-14T05:14:37.853Z"
  },
  "BV1EWFQzZEw4": {
    "startTime": 47.56,
    "endTime": 69.96,
    "duration": 22.4,
    "updatedAt": "2026-02-14T05:15:28.407Z"
  },
  "BV11PcgzWESQ": {
    "startTime": 55.17,
    "endTime": 75.17,
    "duration": 20,
    "updatedAt": "2026-02-14T05:17:53.414Z"
  },
  "BV1X4cgzBESK": {
    "startTime": 36.32,
    "endTime": 56.32,
    "duration": 20,
    "updatedAt": "2026-02-14T05:22:20.946Z"
  },
  "BV1mgF9zLEWg": {
    "startTime": 52.61,
    "endTime": 75.24,
    "duration": 22.63,
    "updatedAt": "2026-02-14T05:24:31.144Z"
  },
  "BV1bLcFzKERh": {
    "startTime": 66,
    "endTime": 91.45,
    "duration": 25.45,
    "updatedAt": "2026-02-14T05:30:27.568Z"
  },
  "BV1fscqz9EjS": {
    "startTime": 189.3,
    "endTime": 211.82,
    "duration": 22.52,
    "updatedAt": "2026-02-14T05:33:03.745Z"
  }
}
